zeno/__init__.py
zeno/__main__.py
zeno/api.py
zeno/backend.py
zeno/classes/base.py
zeno/classes/classes.py
zeno/classes/metadata.py
zeno/classes/projection.py
zeno/classes/report.py
zeno/classes/slice.py
zeno/classes/slice_finder.py
zeno/classes/tag.py
zeno/frontend/build/assets/main.9fb0c2ab.css
zeno/frontend/build/assets/main.c186c0db.js
zeno/frontend/build/favicon.png
zeno/frontend/build/manifest.json
zeno/frontend/build/smui.css
zeno/frontend/build/zeno.png
zeno/frontend/index.html
zeno/frontend/index_og.html
zeno/processing/data_processing.py
zeno/processing/filtering.py
zeno/processing/histogram_processing.py
zeno/processing/projection_processing.py
zeno/processing/slice_finder.py
zeno/runner.py
zeno/server.py
zeno/setup.py
zeno/util.py
zenoml_next-0.6.8.dist-info/LICENSE.md
zenoml_next-0.6.8.dist-info/METADATA
zenoml_next-0.6.8.dist-info/WHEEL
zenoml_next-0.6.8.dist-info/entry_points.txt
zenoml_next-0.6.8.dist-info/RECORD
